{
  "%lld 分钟": {
    "zh-Hant": "%lld 分钟",
    "es": "%lld min",
    "fr": "%lld minutes",
    "de": "%lld min",
    "pt-BR": "%lld minutos",
    "ru": "%lld мин",
    "ar": "%lld دقيقة",
    "hi": "%lld मि",
    "it": "%lld min",
    "th": "%lld นาที",
    "vi": "%lld phút",
    "id": "%lld mnt",
    "tr": "%lld dakika",
    "nl": "%lld min",
    "pl": "%lld min",
    "uk": "%lld хв",
    "ms": "%lld min"
  },
  "%lld 次": {
    "zh-Hant": "%lld 次",
    "es": "%lld sesiones",
    "fr": "%lld séances",
    "de": "%lld Sitzungen",
    "pt-BR": "%lld sessões",
    "ru": "%lld сеансов",
    "ar": "%lld الجلسات",
    "hi": "%lld सत्र",
    "it": "%lld sessioni",
    "th": "%lld เซสชัน",
    "vi": "%lld phiên",
    "id": "%lld sesi",
    "tr": "%lld oturum",
    "nl": "%lld sessies",
    "pl": "%lld sesje",
    "uk": "%lld сесій",
    "ms": "%lld sesi"
  },
  "%@：无专注记录": {
    "zh-Hant": "%@：无專注記录",
    "es": "%@: Sin sesiones de enfoque",
    "fr": "%@ : aucune session de discussion",
    "de": "%@: Keine Fokussitzungen",
    "pt-BR": "%@: Sem sessões de foco",
    "ru": "%@: нет фокус-сессий",
    "ar": "%@: لا توجد جلسات تركيز",
    "hi": "%@: कोई फोकस सत्र नहीं",
    "it": "%@: nessuna sessione focalizzata",
    "th": "%@: ไม่มีเซสชันโฟกัส",
    "vi": "%@: Không có phiên tập trung",
    "id": "%@: Tidak ada sesi fokus",
    "tr": "%@: Odaklanma oturumu yok",
    "nl": "%@: Geen focussessies",
    "pl": "%@: Brak sesji fokusowych",
    "uk": "%@: немає фокус-сеансів",
    "ms": "%@: Tiada sesi fokus"
  },
  "%@\n%@ · 共 %@": {
    "zh-Hant": "%@\n%@ · 共 %@",
    "es": "%@\n%@ · %@ total",
    "fr": "%@\n%@ · %@ total",
    "de": "%@\n%@ · %@ insgesamt",
    "pt-BR": "%@\n%@ · %@ total",
    "ru": "%@\n%@ · %@ всего",
    "ar": "%@\n%@ · %@ المجموع",
    "hi": "%@\n%@ · %@ कुल",
    "it": "%@\n%@ · %@ totale",
    "th": "%@\n%@ · %@ ทั้งหมด",
    "vi": "%@\n%@ · %@ tổng cộng",
    "id": "%@\n%@ · %@ jumlah",
    "tr": "%@\n%@ · %@ toplam",
    "nl": "%@\n%@ · %@ totaal",
    "pl": "%@\n%@ · %@ łącznie",
    "uk": "%@\n%@ · %@ всього",
    "ms": "%@\n%@ · %@ jumlah"
  },
  "%d小时%d分": {
    "zh-Hant": "%d小時%d分",
    "es": "%dh %dm",
    "fr": "%dh %dm",
    "de": "%dh %dm",
    "pt-BR": "%dh %dm",
    "ru": "%dч %dм",
    "ar": "%dح %dم",
    "hi": "%dएच %dएम",
    "it": "%dh %dm",
    "th": "%dชม. %dม",
    "vi": "%dh %dm",
    "id": "%djam %dm",
    "tr": "%dh %ddk",
    "nl": "%dh %dm",
    "pl": "%dh %dm",
    "uk": "%dгод %dхв",
    "ms": "%dh %dm"
  },
  "%d分%d秒": {
    "zh-Hant": "%d分%d秒",
    "es": "%dm %ds",
    "fr": "%dm %ds",
    "de": "%dm %ds",
    "pt-BR": "%dm %ds",
    "ru": "%dм %dс",
    "ar": "%dم %dث",
    "hi": "%dएम %dएस",
    "it": "%dm %ds",
    "th": "%dน %dวิ",
    "vi": "%dm %d giây",
    "id": "%dm %ddtk",
    "tr": "%dm %ds",
    "nl": "%dm %ds",
    "pl": "%dm %ds",
    "uk": "%dм %dс",
    "ms": "%dm %ds"
  },
  "%d秒": {
    "zh-Hant": "%d秒",
    "es": "%ds",
    "fr": "%ds",
    "de": "%ds",
    "pt-BR": "%ds",
    "ru": "%dс",
    "ar": "%dس",
    "hi": "%dएस",
    "it": "%ds",
    "th": "%dส",
    "vi": "%d giây",
    "id": "%ddtk",
    "tr": "%ds",
    "nl": "%ds",
    "pl": "%ds",
    "uk": "%dс",
    "ms": "%ds"
  },
  "M月": {
    "zh-Hant": "MMM",
    "es": "MMM",
    "fr": "MMM",
    "de": "MMM",
    "pt-BR": "MMM",
    "ru": "MMM",
    "ar": "MMM",
    "hi": "MMM",
    "it": "MMM",
    "th": "MMM",
    "vi": "MMM",
    "id": "MMM",
    "tr": "MMM",
    "nl": "MMM",
    "pl": "MMM",
    "uk": "MMM",
    "ms": "MMM"
  },
  "M月d日 EEEE": {
    "zh-Hant": "M月d日 EEEE",
    "es": "d \"de\" MMMM, EEEE",
    "fr": "d MMMM EEEE",
    "de": "EEEE, d. MMMM",
    "pt-BR": "d \"de\" MMMM, EEEE",
    "ru": "d MMMM, EEEE",
    "ar": "d MMMM، EEEE",
    "hi": "d MMMM, EEEE",
    "it": "EEEE d MMMM",
    "th": "EEEE d MMMM",
    "vi": "EEEE, d MMMM",
    "id": "EEEE, d MMMM",
    "tr": "d MMMM EEEE",
    "nl": "EEEE d MMMM",
    "pl": "EEEE, d MMMM",
    "uk": "EEEE, d MMMM",
    "ms": "EEEE, d MMMM"
  },
  "yyyy年M月d日": {
    "zh-Hant": "yyyy年M月d日",
    "es": "d/M/yyyy",
    "fr": "dd/MM/yyyy",
    "de": "dd.MM.yyyy",
    "pt-BR": "dd/MM/yyyy",
    "ru": "dd.MM.yyyy",
    "ar": "d/M/yyyy",
    "hi": "dd/MM/yyyy",
    "it": "dd/MM/yyyy",
    "th": "d/M/yyyy",
    "vi": "d/M/yyyy",
    "id": "d/M/yyyy",
    "tr": "d.MM.yyyy",
    "nl": "d-M-yyyy",
    "pl": "dd.MM.yyyy",
    "uk": "dd.MM.yyyy",
    "ms": "d/M/yyyy"
  },
  "🌳 ×%lld": {
    "zh-Hant": "🌳 ×%lld",
    "es": "🌳 ×%lld",
    "fr": "🌳 ×%lld",
    "de": "🌳 ×%lld",
    "pt-BR": "🌳 ×%lld",
    "ru": "🌳 ×%lld",
    "ar": "🌳 ×%lld",
    "hi": "🌳 ×%lld",
    "it": "🌳 ×%lld",
    "th": "🌳 ×%lld",
    "vi": "🌳 ×%lld",
    "id": "🌳 ×%lld",
    "tr": "🌳 ×%lld",
    "nl": "🌳 ×%lld",
    "pl": "🌳 ×%lld",
    "uk": "🌳 ×%lld",
    "ms": "🌳 ×%lld"
  },
  "一": {
    "zh-Hant": "一",
    "es": "L",
    "fr": "L",
    "de": "M",
    "pt-BR": "S",
    "ru": "П",
    "ar": "ن",
    "hi": "सो",
    "it": "L",
    "th": "จ",
    "vi": "T2",
    "id": "S",
    "tr": "P",
    "nl": "M",
    "pl": "P",
    "uk": "П",
    "ms": "I"
  },
  "三": {
    "zh-Hant": "三",
    "es": "X",
    "fr": "M",
    "de": "M",
    "pt-BR": "Q",
    "ru": "С",
    "ar": "ر",
    "hi": "बु",
    "it": "M",
    "th": "พ",
    "vi": "T4",
    "id": "R",
    "tr": "Ç",
    "nl": "W",
    "pl": "Ś",
    "uk": "С",
    "ms": "R"
  },
  "二": {
    "zh-Hant": "二",
    "es": "M",
    "fr": "M",
    "de": "D",
    "pt-BR": "T",
    "ru": "В",
    "ar": "ث",
    "hi": "मं",
    "it": "M",
    "th": "อ",
    "vi": "T3",
    "id": "S",
    "tr": "S",
    "nl": "D",
    "pl": "W",
    "uk": "В",
    "ms": "S"
  },
  "五": {
    "zh-Hant": "五",
    "es": "V",
    "fr": "V",
    "de": "F",
    "pt-BR": "S",
    "ru": "П",
    "ar": "ج",
    "hi": "शु",
    "it": "V",
    "th": "ศ",
    "vi": "T6",
    "id": "J",
    "tr": "C",
    "nl": "V",
    "pl": "P",
    "uk": "П",
    "ms": "J"
  },
  "六": {
    "zh-Hant": "六",
    "es": "S",
    "fr": "S",
    "de": "S",
    "pt-BR": "S",
    "ru": "С",
    "ar": "س",
    "hi": "श",
    "it": "S",
    "th": "ส",
    "vi": "T7",
    "id": "S",
    "tr": "C",
    "nl": "Z",
    "pl": "S",
    "uk": "С",
    "ms": "S"
  },
  "四": {
    "zh-Hant": "四",
    "es": "J",
    "fr": "J",
    "de": "D",
    "pt-BR": "Q",
    "ru": "Ч",
    "ar": "خ",
    "hi": "गु",
    "it": "G",
    "th": "พฤ",
    "vi": "T5",
    "id": "K",
    "tr": "P",
    "nl": "D",
    "pl": "C",
    "uk": "Ч",
    "ms": "K"
  },
  "日": {
    "zh-Hant": "日",
    "es": "D",
    "fr": "D",
    "de": "S",
    "pt-BR": "D",
    "ru": "В",
    "ar": "ح",
    "hi": "र",
    "it": "D",
    "th": "อา",
    "vi": "CN",
    "id": "M",
    "tr": "P",
    "nl": "Z",
    "pl": "N",
    "uk": "Н",
    "ms": "A"
  },
  "专注": {
    "zh-Hant": "專注",
    "es": "Enfocar",
    "fr": "Se concentrer",
    "de": "Fokus",
    "pt-BR": "Foco",
    "ru": "Фокус",
    "ar": "ركز",
    "hi": "केंद्र",
    "it": "Messa a fuoco",
    "th": "จุดสนใจ",
    "vi": "Tập trung",
    "id": "Fokus",
    "tr": "Odak",
    "nl": "Focus",
    "pl": "Centrum",
    "uk": "Фокус",
    "ms": "Fokus"
  },
  "专注中": {
    "zh-Hant": "專注中",
    "es": "Enfoque",
    "fr": "Mise au point",
    "de": "Fokussieren",
    "pt-BR": "Foco",
    "ru": "Фокусировка",
    "ar": "التركيز",
    "hi": "ध्यान केंद्रित",
    "it": "Messa a fuoco",
    "th": "การมุ่งเน้น",
    "vi": "Lấy nét",
    "id": "Fokus",
    "tr": "Odaklanma",
    "nl": "Focussen",
    "pl": "Skupienie",
    "uk": "Фокусування",
    "ms": "Memberi tumpuan"
  },
  "专注完成": {
    "zh-Hant": "專注完成",
    "es": "Enfoque completo",
    "fr": "Mise au point terminée",
    "de": "Fokus abgeschlossen",
    "pt-BR": "Foco concluído",
    "ru": "Фокус завершен",
    "ar": "التركيز كامل",
    "hi": "फोकस पूर्ण",
    "it": "Messa a fuoco completata",
    "th": "โฟกัสเสร็จสมบูรณ์",
    "vi": "Tập trung hoàn thành",
    "id": "Fokus Selesai",
    "tr": "Odaklanma Tamamlandı",
    "nl": "Focus voltooid",
    "pl": "Skupienie zakończone",
    "uk": "Фокус завершено",
    "ms": "Fokus Selesai"
  },
  "专注完成，猫粮已领取": {
    "zh-Hant": "專注完成，貓粮已领取",
    "es": "Sesión terminada, trato reclamado",
    "fr": "Séance terminée, friandise réclamée",
    "de": "Sitzung beendet, Behandlung beansprucht",
    "pt-BR": "Sessão concluída, tratamento reivindicado",
    "ru": "Сеанс завершен, лечение заявлено",
    "ar": "انتهت الجلسة، تمت المطالبة بالعلاج",
    "hi": "सत्र हो गया, उपचार का दावा किया गया",
    "it": "Sessione terminata, trattamento richiesto",
    "th": "เซสชันเสร็จสิ้น รับการรักษาแล้ว",
    "vi": "Phiên đã hoàn tất, điều trị đã được yêu cầu",
    "id": "Sesi selesai, suguhan diklaim",
    "tr": "Oturum tamamlandı, tedavi talep edildi",
    "nl": "Sessie gedaan, behandeling geclaimd",
    "pl": "Sesja zakończona, leczenie zgłoszone",
    "uk": "Сеанс виконано, лікування заявлено",
    "ms": "Sesi selesai, rawatan dituntut"
  },
  "专注热力图": {
    "zh-Hant": "專注熱力圖",
    "es": "Mapa de calor de enfoque",
    "fr": "Focus sur la carte thermique",
    "de": "Fokus-Heatmap",
    "pt-BR": "Mapa de calor de foco",
    "ru": "Тепловая карта фокуса",
    "ar": "خريطة التركيز الحرارية",
    "hi": "फोकस हीटमैप",
    "it": "Concentrarsi sulla mappa termica",
    "th": "โฟกัสแผนที่ความร้อน",
    "vi": "Bản đồ nhiệt tập trung",
    "id": "Peta Panas Fokus",
    "tr": "Odak Isı Haritası",
    "nl": "Focus-hittekaart",
    "pl": "Mapa cieplna ostrości",
    "uk": "Теплова карта фокусу",
    "ms": "Peta Haba Fokus"
  },
  "为你梦想蓄力一次": {
    "zh-Hant": "为你梦想蓄力一次",
    "es": "combustible para tus sueños",
    "fr": "carburant pour vos rêves",
    "de": "Treibstoff für Ihre Träume",
    "pt-BR": "combustível para seus sonhos",
    "ru": "топливо для твоей мечты",
    "ar": "وقود لأحلامك",
    "hi": "आपके सपनों के लिए ईंधन",
    "it": "carburante per i tuoi sogni",
    "th": "เชื้อเพลิงเพื่อความฝันของคุณ",
    "vi": "tiếp nhiên liệu cho ước mơ của bạn",
    "id": "bahan bakar untuk impian Anda",
    "tr": "hayallerin için yakıt",
    "nl": "brandstof voor je dromen",
    "pl": "paliwo dla Twoich marzeń",
    "uk": "паливо для ваших мрій",
    "ms": "bahan bakar untuk impian anda"
  },
  "为梦想蓄力一次": {
    "zh-Hant": "为梦想蓄力一次",
    "es": "combustible para tus sueños",
    "fr": "carburant pour vos rêves",
    "de": "Treibstoff für Ihre Träume",
    "pt-BR": "combustível para seus sonhos",
    "ru": "топливо для твоей мечты",
    "ar": "وقود لأحلامك",
    "hi": "आपके सपनों के लिए ईंधन",
    "it": "carburante per i tuoi sogni",
    "th": "เชื้อเพลิงเพื่อความฝันของคุณ",
    "vi": "tiếp nhiên liệu cho ước mơ của bạn",
    "id": "bahan bakar untuk impian Anda",
    "tr": "hayallerin için yakıt",
    "nl": "brandstof voor je dromen",
    "pl": "paliwo dla Twoich marzeń",
    "uk": "паливо для ваших мрій",
    "ms": "bahan bakar untuk impian anda"
  },
  "云养猫": {
    "zh-Hant": "雲养貓",
    "es": "gato nube",
    "fr": "Chat Nuage",
    "de": "Wolkenkatze",
    "pt-BR": "Gato das Nuvens",
    "ru": "Облачный кот",
    "ar": "سحابة القط",
    "hi": "बादल बिल्ली",
    "it": "Gatto delle nuvole",
    "th": "แมวเมฆ",
    "vi": "Mèo Mây",
    "id": "Kucing Awan",
    "tr": "Bulut Kedisi",
    "nl": "Wolken kat",
    "pl": "Obłoczny Kot",
    "uk": "Хмарний кіт",
    "ms": "Kucing Awan"
  },
  "今天": {
    "zh-Hant": "今天",
    "es": "Hoy",
    "fr": "Aujourd'hui",
    "de": "Heute",
    "pt-BR": "Hoje",
    "ru": "Сегодня",
    "ar": "اليوم",
    "hi": "आज",
    "it": "Oggi",
    "th": "วันนี้",
    "vi": "Hôm nay",
    "id": "Hari ini",
    "tr": "Bugün",
    "nl": "Vandaag",
    "pl": "Dzisiaj",
    "uk": "Сьогодні",
    "ms": "Hari ini"
  },
  "今天你陪了我 %lld 分钟，好开心！": {
    "zh-Hant": "今天你陪了我 %lld 分钟，好開心！",
    "es": "Te concentraste conmigo durante %lld minutos hoy. ¡Qué feliz!",
    "fr": "Vous vous êtes concentré sur moi pendant %lld minutes aujourd'hui. Tellement heureux !",
    "de": "Du hast dich heute %lld Minuten lang auf mich konzentriert. So glücklich!",
    "pt-BR": "Você se concentrou comigo por %lld minutos hoje. Tão feliz!",
    "ru": "Сегодня вы сосредоточились со мной на %lld минут. Так счастлив!",
    "ar": "لقد ركزت معي لمدة %lld دقيقة اليوم. سعيد جدا!",
    "hi": "आज आपने मेरे साथ %lld मिनट तक ध्यान केंद्रित किया। इतना खुश!",
    "it": "Ti sei concentrato con me per %lld minuti oggi. Così felice!",
    "th": "วันนี้คุณจดจ่อกับฉันเป็นเวลา %lld นาที มีความสุขมาก!",
    "vi": "Hôm nay bạn đã tập trung cùng tôi trong %lld phút. Thật hạnh phúc!",
    "id": "Anda fokus dengan saya selama %lld menit hari ini. Senang sekali!",
    "tr": "Bugün %lld dakika boyunca bana odaklandın. Çok mutlu!",
    "nl": "Je hebt vandaag %lld minuten met mij gefocust. Zo blij!",
    "pl": "Skupiałeś się dzisiaj ze mną przez %lld minut. Taki szczęśliwy!",
    "uk": "Сьогодні ви зосереджувалися на мені протягом %lld хвилин. Так щасливий!",
    "ms": "Anda memberi tumpuan dengan saya selama %lld minit hari ini. sangat gembira!"
  },
  "今天状态不错～": {
    "zh-Hant": "今天状態不错～",
    "es": "Me siento genial hoy ~",
    "fr": "Je me sens bien aujourd'hui ~",
    "de": "Ich fühle mich heute großartig~",
    "pt-BR": "Me sentindo ótimo hoje~",
    "ru": "Чувствую себя сегодня прекрасно~",
    "ar": "شعور عظيم اليوم ~",
    "hi": "आज बहुत अच्छा लग रहा है~",
    "it": "Mi sento benissimo oggi~",
    "th": "วันนี้รู้สึกดีจัง~",
    "vi": "Cảm giác hôm nay thật tuyệt vời~",
    "id": "Merasa luar biasa hari ini~",
    "tr": "Bugün harika hissediyorum~",
    "nl": "Ik voel me geweldig vandaag~",
    "pl": "Czuję się dzisiaj świetnie~",
    "uk": "Почуваюся чудово сьогодні~",
    "ms": "Rasa hebat hari ini~"
  },
  "全部汇总": {
    "zh-Hant": "全部汇總",
    "es": "Todo el tiempo",
    "fr": "Tout le temps",
    "de": "Alle Zeit",
    "pt-BR": "Todos os tempos",
    "ru": "Все время",
    "ar": "كل الوقت",
    "hi": "पूरे समय",
    "it": "Tutto il tempo",
    "th": "ตลอดเวลา",
    "vi": "mọi lúc",
    "id": "Sepanjang Waktu",
    "tr": "Tüm Zamanlar",
    "nl": "Altijd",
    "pl": "Cały czas",
    "uk": "Весь час",
    "ms": "Sepanjang Masa"
  },
  "共 %lld 次": {
    "zh-Hant": "共 %lld 次",
    "es": "%lld sesiones totales",
    "fr": "%lld sessions au total",
    "de": "%lld Sitzungen insgesamt",
    "pt-BR": "Total de %lld sessões",
    "ru": "Всего %lld сеансов",
    "ar": "%lld إجمالي الجلسات",
    "hi": "%lld कुल सत्र",
    "it": "%lld sessioni totali",
    "th": "%lld เซสชันทั้งหมด",
    "vi": "Tổng cộng %lld phiên",
    "id": "%lld total sesi",
    "tr": "Toplam %lld oturum",
    "nl": "%lld sessies totaal",
    "pl": "Łącznie %lld sesji",
    "uk": "Усього %lld сеансів",
    "ms": "%lld sesi jumlah"
  },
  "关闭后不显示任何养猫相关功能。": {
    "zh-Hant": "關闭後不顯示任何养貓相關功能。",
    "es": "Cuando está desactivado, todas las funciones del compañero gato están ocultas.",
    "fr": "Lorsqu'elle est désactivée, toutes les fonctionnalités des compagnons de chat sont masquées.",
    "de": "Wenn diese Option deaktiviert ist, sind alle Funktionen für Katzenbegleiter ausgeblendet.",
    "pt-BR": "Quando desativado, todos os recursos do companheiro gato ficam ocultos.",
    "ru": "Если функция отключена, все функции кошки-компаньона скрыты.",
    "ar": "عند إيقاف التشغيل، تكون جميع ميزات رفيق القطط مخفية.",
    "hi": "बंद होने पर, सभी बिल्ली साथी सुविधाएँ छिपी रहती हैं।",
    "it": "Quando è disattivata, tutte le funzionalità del compagno gatto sono nascoste.",
    "th": "เมื่อปิด คุณสมบัติสหายแมวทั้งหมดจะถูกซ่อนไว้",
    "vi": "Khi tắt, tất cả các tính năng đồng hành của mèo sẽ bị ẩn.",
    "id": "Jika tidak aktif, semua fitur pendamping kucing disembunyikan.",
    "tr": "Kapatıldığında tüm kedi arkadaşı özellikleri gizlenir.",
    "nl": "Als deze functie is uitgeschakeld, zijn alle functies voor kattengezellen verborgen.",
    "pl": "Gdy opcja ta jest wyłączona, wszystkie funkcje kociego towarzysza są ukryte.",
    "uk": "Коли вимкнено, усі функції котів-компаньйонів приховані.",
    "ms": "Apabila dimatikan, semua ciri teman kucing disembunyikan."
  },
  "击退拖延一次": {
    "zh-Hant": "擊退拖延一次",
    "es": "vencer la procrastinación",
    "fr": "vaincre la procrastination",
    "de": "Schlagen Sie den Aufschub",
    "pt-BR": "vencer a procrastinação",
    "ru": "победить прокрастинацию",
    "ar": "تغلب على المماطلة",
    "hi": "विलंब को हराओ",
    "it": "battere la procrastinazione",
    "th": "เอาชนะการผัดวันประกันพรุ่ง",
    "vi": "đánh bại sự trì hoãn",
    "id": "mengalahkan penundaan",
    "tr": "ertelemeyi yenmek",
    "nl": "uitstelgedrag verslaan",
    "pl": "pokonać prokrastynację",
    "uk": "перемогти прокрастинацію",
    "ms": "mengalahkan penangguhan"
  },
  "夺回注意力一次": {
    "zh-Hant": "奪回注意力一次",
    "es": "reclamé tu atención",
    "fr": "a récupéré votre attention",
    "de": "hat deine Aufmerksamkeit zurückerobert",
    "pt-BR": "recuperou sua atenção",
    "ru": "вернул твое внимание",
    "ar": "استعادت انتباهك",
    "hi": "आपका ध्यान पुनः प्राप्त किया",
    "it": "recuperato la tua attenzione",
    "th": "เรียกความสนใจของคุณกลับมาแล้ว",
    "vi": "lấy lại sự chú ý của bạn",
    "id": "mendapatkan kembali perhatianmu",
    "tr": "dikkatinizi geri kazandınız",
    "nl": "heeft uw aandacht weer teruggevorderd",
    "pl": "odzyskał twoją uwagę",
    "uk": "привернув вашу увагу",
    "ms": "menarik semula perhatian anda"
  },
  "虽然没完成，但也陪了我一会儿～": {
    "zh-Hant": "虽然没完成，但也陪了我一会儿～",
    "es": "No terminé, pero gracias por hacerme compañía~",
    "fr": "Je n'ai pas fini, mais merci de me tenir compagnie ~",
    "de": "Ich bin noch nicht fertig, aber danke, dass du mir Gesellschaft geleistet hast~",
    "pt-BR": "Não terminei, mas obrigado por me fazer companhia~",
    "ru": "Не закончил, но спасибо, что составили мне компанию~",
    "ar": "لم أنتهي، لكن شكرًا على مرافقتي ~",
    "hi": "ख़त्म नहीं हुआ, लेकिन मेरा साथ देने के लिए धन्यवाद~",
    "it": "Non ho finito, ma grazie per avermi tenuto compagnia~",
    "th": "ยังไม่จบ แต่ขอบคุณที่คอยเป็นเพื่อนกัน~",
    "vi": "Chưa hoàn thành nhưng cảm ơn vì đã đồng hành cùng tôi~",
    "id": "Belum selesai, tapi terima kasih sudah menemaniku~",
    "tr": "Bitirmedim ama bana eşlik ettiğin için teşekkürler~",
    "nl": "Ik ben nog niet klaar, maar bedankt dat je me gezelschap hield~",
    "pl": "Nie skończyłem, ale dziękuję za dotrzymanie mi towarzystwa~",
    "uk": "Не закінчив, але дякую, що склав мені компанію ~",
    "ms": "Tidak selesai, tetapi terima kasih kerana menemani saya ~"
  },
  "含完成、暂停与提前结束": {
    "zh-Hant": "含完成、暂停与提前結束",
    "es": "Incluye sesiones completadas, pausadas y finalizadas anticipadamente.",
    "fr": "Comprend les sessions terminées, interrompues et terminées plus tôt",
    "de": "Beinhaltet abgeschlossene, pausierte und vorzeitig beendete Sitzungen",
    "pt-BR": "Inclui sessões concluídas, pausadas e encerradas antecipadamente",
    "ru": "Включает завершенные, приостановленные и досрочно завершенные сеансы.",
    "ar": "يتضمن الجلسات المكتملة والمتوقفة مؤقتًا والمنتهية مبكرًا",
    "hi": "इसमें पूर्ण, रुके हुए और जल्दी समाप्त हुए सत्र शामिल हैं",
    "it": "Include sessioni completate, in pausa e con conclusione anticipata",
    "th": "รวมถึงเซสชันที่เสร็จสิ้นแล้ว หยุดชั่วคราว และสิ้นสุดก่อนกำหนด",
    "vi": "Bao gồm các phiên đã hoàn thành, tạm dừng và kết thúc sớm",
    "id": "Termasuk sesi yang diselesaikan, dijeda, dan diakhiri lebih awal",
    "tr": "Tamamlanan, duraklatılan ve erken sona eren oturumları içerir",
    "nl": "Omvat voltooide, onderbroken en vroegtijdig beëindigde sessies",
    "pl": "Obejmuje sesje ukończone, wstrzymane i zakończone wcześniej",
    "uk": "Включає завершені, призупинені та достроково завершені сеанси",
    "ms": "Termasuk sesi selesai, dijeda dan tamat awal"
  },
  "基于 %lld 个活跃日": {
    "zh-Hant": "基于 %lld 个活跃日",
    "es": "Basado en %lld días activos",
    "fr": "Basé sur %lld jours actifs",
    "de": "Basierend auf %lld aktiven Tagen",
    "pt-BR": "Com base em %lld dias ativos",
    "ru": "На основе %lld активных дней",
    "ar": "بناءً على %lld من الأيام النشطة",
    "hi": "%lld सक्रिय दिनों के आधार पर",
    "it": "Basato su %lld giorni attivi",
    "th": "อ้างอิงจาก %lld วันที่ใช้งาน",
    "vi": "Dựa trên %lld ngày hoạt động",
    "id": "Berdasarkan %lld hari aktif",
    "tr": "%lld aktif güne dayalı",
    "nl": "Gebaseerd op %lld actieve dagen",
    "pl": "Na podstawie %lld aktywnych dni",
    "uk": "На основі %lld активних днів",
    "ms": "Berdasarkan %lld hari aktif"
  },
  "多": {
    "zh-Hant": "多",
    "es": "Más",
    "fr": "Plus",
    "de": "Mehr",
    "pt-BR": "Mais",
    "ru": "Более",
    "ar": "أكثر",
    "hi": "अधिक",
    "it": "Di più",
    "th": "มากกว่า",
    "vi": "Hơn",
    "id": "Lagi",
    "tr": "Daha",
    "nl": "Meer",
    "pl": "Więcej",
    "uk": "більше",
    "ms": "Lagi"
  },
  "好棒！吃到猫粮啦": {
    "zh-Hant": "好棒！吃到貓粮啦",
    "es": "¡Hurra! ¡Tengo un regalo!",
    "fr": "Ouais! J'ai eu un régal !",
    "de": "Juhuu! Habe ein Leckerli bekommen!",
    "pt-BR": "Yay! Recebi uma delícia!",
    "ru": "Ура! Получил удовольствие!",
    "ar": "ياي! حصلت على علاج!",
    "hi": "वाह! एक दावत मिली!",
    "it": "Sìì! Ho una sorpresa!",
    "th": "เย้! ได้รับการรักษา!",
    "vi": "Đúng! Có một điều trị!",
    "id": "Hore! Dapat hadiah!",
    "tr": "Yay! Bir ikramım var!",
    "nl": "Jawel! Ik heb een traktatie!",
    "pl": "Tak! Mam ucztę!",
    "uk": "ура! Отримав частування!",
    "ms": "Yay! Dapat hadiah!"
  },
  "好开心": {
    "zh-Hant": "好開心",
    "es": "tan feliz",
    "fr": "Tellement heureux",
    "de": "So glücklich",
    "pt-BR": "Tão feliz",
    "ru": "Так счастлив",
    "ar": "سعيدة جدا",
    "hi": "इतना खुश",
    "it": "Così felice",
    "th": "มีความสุขมาก",
    "vi": "Thật hạnh phúc",
    "id": "Sangat senang",
    "tr": "Çok mutlu",
    "nl": "Zo blij",
    "pl": "Taki szczęśliwy",
    "uk": "Такий щасливий",
    "ms": "sangat gembira"
  },
  "怎么停下来了？": {
    "zh-Hant": "怎么停下来了？",
    "es": "¿Por qué paraste?",
    "fr": "Pourquoi as-tu arrêté ?",
    "de": "Warum hast du aufgehört?",
    "pt-BR": "Por que você parou?",
    "ru": "Почему ты остановился?",
    "ar": "لماذا توقفت؟",
    "hi": "तुम रुक क्यों गए?",
    "it": "Perché ti sei fermato?",
    "th": "ทำไมคุณถึงหยุด?",
    "vi": "Tại sao bạn dừng lại?",
    "id": "Mengapa kamu berhenti?",
    "tr": "Neden durdun?",
    "nl": "Waarom ben je gestopt?",
    "pl": "Dlaczego się zatrzymałeś?",
    "uk": "Чому ти зупинився?",
    "ms": "Kenapa awak berhenti?"
  },
  "幼猫": {
    "zh-Hant": "幼貓",
    "es": "Gatito",
    "fr": "Chaton",
    "de": "Kätzchen",
    "pt-BR": "Gatinho",
    "ru": "Котенок",
    "ar": "هريرة",
    "hi": "बिल्ली का बच्चा",
    "it": "Gattino",
    "th": "ลูกแมว",
    "vi": "mèo con",
    "id": "Anak kucing",
    "tr": "yavru kedi",
    "nl": "Katje",
    "pl": "Kotek",
    "uk": "кошеня",
    "ms": "anak kucing"
  },
  "成猫": {
    "zh-Hant": "成貓",
    "es": "gato adulto",
    "fr": "Chat adulte",
    "de": "Erwachsene Katze",
    "pt-BR": "Gato adulto",
    "ru": "Взрослая кошка",
    "ar": "قطة بالغة",
    "hi": "वयस्क बिल्ली",
    "it": "Gatto adulto",
    "th": "แมวโต",
    "vi": "Mèo trưởng thành",
    "id": "Kucing Dewasa",
    "tr": "Yetişkin Kedi",
    "nl": "Volwassen kat",
    "pl": "Dorosły kot",
    "uk": "Дорослий кіт",
    "ms": "Kucing Dewasa"
  },
  "恢复为默认时长": {
    "zh-Hant": "恢复为預設時長",
    "es": "Restablecer la duración predeterminada",
    "fr": "Réinitialiser la durée par défaut",
    "de": "Auf Standarddauer zurücksetzen",
    "pt-BR": "Redefinir para duração padrão",
    "ru": "Сбросить продолжительность по умолчанию",
    "ar": "إعادة التعيين إلى المدة الافتراضية",
    "hi": "डिफ़ॉल्ट अवधि पर रीसेट करें",
    "it": "Ripristina la durata predefinita",
    "th": "รีเซ็ตเป็นระยะเวลาเริ่มต้น",
    "vi": "Đặt lại về thời lượng mặc định",
    "id": "Atur Ulang ke Durasi Default",
    "tr": "Varsayılan Süreye Sıfırla",
    "nl": "Reset naar standaardduur",
    "pl": "Przywróć domyślny czas trwania",
    "uk": "Відновити тривалість за замовчуванням",
    "ms": "Tetapkan Semula kepada Tempoh Lalai"
  },
  "拯救前额叶一次": {
    "zh-Hant": "拯救前额叶一次",
    "es": "salvó tu corteza prefrontal",
    "fr": "sauvé votre cortex préfrontal",
    "de": "hat Ihren präfrontalen Kortex gerettet",
    "pt-BR": "salvou seu córtex pré-frontal",
    "ru": "спас твою префронтальную кору",
    "ar": "أنقذت قشرة الفص الجبهي لديك",
    "hi": "आपके प्रीफ्रंटल कॉर्टेक्स को बचाया",
    "it": "salvato la tua corteccia prefrontale",
    "th": "บันทึกเยื่อหุ้มสมองส่วนหน้าของคุณ",
    "vi": "đã cứu vỏ não trước trán của bạn",
    "id": "menyelamatkan korteks prefrontal Anda",
    "tr": "prefrontal korteksinizi kurtardı",
    "nl": "heeft je prefrontale cortex gered",
    "pl": "ocalił twoją korę przedczołową",
    "uk": "врятував вашу префронтальну кору",
    "ms": "menyelamatkan korteks prefrontal anda"
  },
  "积攒实力一次": {
    "zh-Hant": "積攒实力一次",
    "es": "impulso generado",
    "fr": "pris une dynamique",
    "de": "Schwung aufgebaut",
    "pt-BR": "impulso construído",
    "ru": "придал импульс",
    "ar": "الزخم المبني",
    "hi": "निर्मित गति",
    "it": "slancio costruito",
    "th": "โมเมนตัมที่สร้างขึ้น",
    "vi": "đà xây dựng",
    "id": "momentum yang dibangun",
    "tr": "inşa edilmiş ivme",
    "nl": "momentum opgebouwd",
    "pl": "zbudowany rozmach",
    "uk": "збудований імпульс",
    "ms": "momentum yang dibina"
  },
  "日均次数": {
    "zh-Hant": "日均次数",
    "es": "Promedio diario Sesiones",
    "fr": "Moy. quotidienne. Séances",
    "de": "Täglicher Durchschn. Sitzungen",
    "pt-BR": "Média diária Sessões",
    "ru": "Средн. за день Сессии",
    "ar": "المتوسط ​​اليومي الجلسات",
    "hi": "दैनिक औसत. सत्र",
    "it": "Media giornaliera Sessioni",
    "th": "เฉลี่ยรายวัน เซสชัน",
    "vi": "Trung bình hàng ngày Phiên",
    "id": "Rata-rata Harian Sesi",
    "tr": "Günlük Ort. Oturumlar",
    "nl": "Dagelijks gem. Sessies",
    "pl": "Średnia dzienna Sesje",
    "uk": "Середнє щоденне Сеанси",
    "ms": "Purata Harian Sesi"
  },
  "日均时长": {
    "zh-Hant": "日均時長",
    "es": "Promedio diario Duración",
    "fr": "Moy. quotidienne. Durée",
    "de": "Täglicher Durchschn. Dauer",
    "pt-BR": "Média diária Duração",
    "ru": "Средн. за день Продолжительность",
    "ar": "المتوسط ​​اليومي مدة",
    "hi": "दैनिक औसत. अवधि",
    "it": "Media giornaliera Durata",
    "th": "เฉลี่ยรายวัน ระยะเวลา",
    "vi": "Trung bình hàng ngày Khoảng thời gian",
    "id": "Rata-rata Harian Lamanya",
    "tr": "Günlük Ort. Süre",
    "nl": "Dagelijks gem. Duur",
    "pl": "Średnia dzienna Czas trwania",
    "uk": "Середнє щоденне Тривалість",
    "ms": "Purata Harian Tempoh"
  },
  "平均每天专注时长": {
    "zh-Hant": "平均每天專注時長",
    "es": "Tiempo medio diario de concentración",
    "fr": "Temps de concentration quotidien moyen",
    "de": "Durchschnittliche tägliche Fokuszeit",
    "pt-BR": "Tempo médio diário de foco",
    "ru": "Среднее ежедневное время концентрации",
    "ar": "متوسط ​​وقت التركيز اليومي",
    "hi": "औसत दैनिक फोकस समय",
    "it": "Tempo medio di concentrazione giornaliero",
    "th": "เวลาโฟกัสเฉลี่ยรายวัน",
    "vi": "Thời gian tập trung trung bình hàng ngày",
    "id": "Waktu fokus harian rata-rata",
    "tr": "Ortalama günlük odaklanma süresi",
    "nl": "Gemiddelde dagelijkse focustijd",
    "pl": "Średni dzienny czas skupienia",
    "uk": "Середній щоденний час концентрації уваги",
    "ms": "Purata masa fokus harian"
  },
  "已专注%lld分钟，%@": {
    "zh-Hant": "已專注%lld分钟，%@",
    "es": "Enfocado durante %lld minutos — %@",
    "fr": "Concentré pendant %lld minutes — %@",
    "de": "Konzentriert für %lld Minuten – %@",
    "pt-BR": "Focado por %lld minutos — %@",
    "ru": "Сосредоточен на %lld минут — %@",
    "ar": "تم التركيز لمدة %lld دقيقة — %@",
    "hi": "%lld मिनट तक केंद्रित - %@",
    "it": "Concentrato per %lld minuti — %@",
    "th": "โฟกัสเป็นเวลา %lld นาที — %@",
    "vi": "Tập trung trong %lld phút — %@",
    "id": "Difokuskan selama %lld menit — %@",
    "tr": "%lld dakika boyunca odaklanıldı — %@",
    "nl": "Gefocust gedurende %lld minuten — %@",
    "pl": "Skupiony przez %lld minut — %@",
    "uk": "Зосереджено %lld хвилин — %@",
    "ms": "Fokus selama %lld minit — %@"
  },
  "已暂停": {
    "zh-Hant": "已暂停",
    "es": "En pausa",
    "fr": "En pause",
    "de": "Angehalten",
    "pt-BR": "Pausado",
    "ru": "Приостановлено",
    "ar": "متوقف مؤقتًا",
    "hi": "रुका हुआ",
    "it": "In pausa",
    "th": "หยุดชั่วคราว",
    "vi": "Đã tạm dừng",
    "id": "Dijeda",
    "tr": "Duraklatıldı",
    "nl": "Gepauzeerd",
    "pl": "Wstrzymano",
    "uk": "Призупинено",
    "ms": "Dijeda"
  },
  "开启后会有像素小猫陪伴专注；桌面浮窗可将小猫放在桌面上。": {
    "zh-Hant": "開啟後会有像素小貓陪伴專注；桌面浮窗可将小貓放在桌面上。",
    "es": "Un gato pixelado te hará compañía. El flotador de escritorio coloca al gato en tu pantalla.",
    "fr": "Un chat pixel vous tiendra compagnie. Le flotteur du bureau place le chat sur votre écran.",
    "de": "Eine Pixelkatze wird Ihnen Gesellschaft leisten. Desktop Float platziert die Katze auf Ihrem Bildschirm.",
    "pt-BR": "Um gato pixel fará companhia a você. O flutuador da área de trabalho coloca o gato na tela.",
    "ru": "Пиксельный кот составит вам компанию. Desktop float помещает кошку на экран.",
    "ar": "قطة البيكسل سوف تبقيك بصحبة. سطح المكتب يضع القطة على شاشتك.",
    "hi": "एक पिक्सेल बिल्ली आपका साथ देगी। डेस्कटॉप फ्लोट बिल्ली को आपकी स्क्रीन पर रखता है।",
    "it": "Un gatto pixel ti terrà compagnia. Il float del desktop posiziona il gatto sullo schermo.",
    "th": "แมวพิกเซลจะคอยเป็นเพื่อนคุณ เดสก์ท็อปลอยวางแมวบนหน้าจอของคุณ",
    "vi": "Một chú mèo pixel sẽ đồng hành cùng bạn. Máy tính để bàn nổi đặt con mèo trên màn hình của bạn.",
    "id": "Seekor kucing piksel akan menemani Anda. Desktop float menempatkan kucing di layar Anda.",
    "tr": "Bir piksel kedi size eşlik edecek. Masaüstü kayan kediyi ekranınıza yerleştirir.",
    "nl": "Een pixelkat houdt je gezelschap. Desktop float plaatst de kat op uw scherm.",
    "pl": "Pikselowy kot dotrzyma Ci towarzystwa. Pulpit pływakowy umieszcza kota na ekranie.",
    "uk": "Компанію вам складе піксельний кіт. Desktop float розміщує кота на вашому екрані.",
    "ms": "Kucing piksel akan menemani anda. Terapung desktop meletakkan kucing pada skrin anda."
  },
  "开始": {
    "zh-Hant": "開始",
    "es": "Comenzar",
    "fr": "Commencer",
    "de": "Start",
    "pt-BR": "Começar",
    "ru": "Начинать",
    "ar": "يبدأ",
    "hi": "शुरू",
    "it": "Inizio",
    "th": "เริ่ม",
    "vi": "Bắt đầu",
    "id": "Awal",
    "tr": "Başlangıç",
    "nl": "Begin",
    "pl": "Start",
    "uk": "старт",
    "ms": "Mulakan"
  },
  "开始云养猫": {
    "zh-Hant": "開始雲养貓",
    "es": "Habilitar gato en la nube",
    "fr": "Activer Cloud Cat",
    "de": "Aktivieren Sie Cloud Cat",
    "pt-BR": "Ativar Cloud Cat",
    "ru": "Включить Cloud Cat",
    "ar": "تمكين سحابة القط",
    "hi": "क्लाउड कैट सक्षम करें",
    "it": "Abilita Cloud Cat",
    "th": "เปิดใช้งานคลาวด์แคท",
    "vi": "Kích hoạt Cloud Cat",
    "id": "Aktifkan Cloud Cat",
    "tr": "Cloud Cat'i etkinleştirin",
    "nl": "Schakel Cloud Cat. in",
    "pl": "Włącz Cloud Cat",
    "uk": "Увімкнути Cloud Cat",
    "ms": "Dayakan Cloud Cat"
  },
  "开始专注": {
    "zh-Hant": "開始專注",
    "es": "Iniciar enfoque",
    "fr": "Démarrer la mise au point",
    "de": "Starten Sie den Fokus",
    "pt-BR": "Iniciar foco",
    "ru": "Начать фокус",
    "ar": "ابدأ التركيز",
    "hi": "फोकस प्रारंभ करें",
    "it": "Avvia la messa a fuoco",
    "th": "เริ่มโฟกัส",
    "vi": "Bắt đầu lấy nét",
    "id": "Mulai Fokus",
    "tr": "Odaklanmayı Başlat",
    "nl": "Begin met focussen",
    "pl": "Uruchom Fokus",
    "uk": "Розпочати фокус",
    "ms": "Mula Fokus"
  },
  "所有记录合计": {
    "zh-Hant": "所有記录合计",
    "es": "Todas las sesiones combinadas",
    "fr": "Toutes séances confondues",
    "de": "Alle Sitzungen zusammen",
    "pt-BR": "Todas as sessões combinadas",
    "ru": "Все сеансы вместе взятые",
    "ar": "جميع الجلسات مجتمعة",
    "hi": "सभी सत्र संयुक्त",
    "it": "Tutte le sessioni combinate",
    "th": "เซสชันทั้งหมดรวมกัน",
    "vi": "Tất cả các phiên kết hợp",
    "id": "Semua sesi digabungkan",
    "tr": "Tüm oturumlar birleştirildi",
    "nl": "Alle sessies gecombineerd",
    "pl": "Wszystkie sesje połączone",
    "uk": "Усі сеанси разом",
    "ms": "Semua sesi digabungkan"
  },
  "喵喵…好久没陪我啦": {
    "zh-Hant": "喵喵…好久没陪我啦",
    "es": "Miau… ha pasado un tiempo",
    "fr": "Miaou… ça fait longtemps",
    "de": "Miau... es ist schon eine Weile her",
    "pt-BR": "Miau… já faz um tempo",
    "ru": "Мяу... прошло много времени",
    "ar": "مواء... لقد مر وقت طويل",
    "hi": "म्याऊं... बहुत समय हो गया",
    "it": "Miao... è passato un po' di tempo",
    "th": "เหมียว… หายไปนานเลย",
    "vi": "Meo... đã được một lúc rồi",
    "id": "Meong… sudah lama tidak bertemu",
    "tr": "Miyav… uzun zaman oldu",
    "nl": "Miauw... het is alweer een tijdje geleden",
    "pl": "Miau… minęło trochę czasu",
    "uk": "Мяу… минуло час",
    "ms": "Meow… dah agak lama"
  },
  "喵…好久没陪我啦": {
    "zh-Hant": "喵…好久没陪我啦",
    "es": "Miau… ha pasado un tiempo",
    "fr": "Miaou… ça fait longtemps",
    "de": "Miau... es ist schon eine Weile her",
    "pt-BR": "Miau… já faz um tempo",
    "ru": "Мяу... прошло много времени",
    "ar": "مواء... لقد مر وقت طويل",
    "hi": "म्याऊं... बहुत समय हो गया",
    "it": "Miao... è passato un po' di tempo",
    "th": "เหมียว… หายไปนานเลย",
    "vi": "Meo... đã được một lúc rồi",
    "id": "Meong… sudah lama tidak bertemu",
    "tr": "Miyav… uzun zaman oldu",
    "nl": "Miauw... het is alweer een tijdje geleden",
    "pl": "Miau… minęło trochę czasu",
    "uk": "Мяу… минуло час",
    "ms": "Meow… dah agak lama"
  },
  "咪咪": {
    "zh-Hant": "咪咪",
    "es": "mimí",
    "fr": "Mimi",
    "de": "Mimi",
    "pt-BR": "Mimi",
    "ru": "Мими",
    "ar": "ميمي",
    "hi": "मिमी",
    "it": "Mimì",
    "th": "มีมี่",
    "vi": "Mimi",
    "id": "Mimi",
    "tr": "Mimi",
    "nl": "Mimi",
    "pl": "Mimi",
    "uk": "Мімі",
    "ms": "Mimi"
  },
  "完成 %lld 次 %@": {
    "zh-Hant": "完成 %lld 次 %@",
    "es": "%lld sesiones %@",
    "fr": "%lld séances %@",
    "de": "%lld Sitzungen %@",
    "pt-BR": "%lld sessões %@",
    "ru": "%lld сеансов %@",
    "ar": "%lld الجلسات %@",
    "hi": "%lld सत्र %@",
    "it": "%lld sessioni %@",
    "th": "%lld เซสชัน %@",
    "vi": "%lld phiên %@",
    "id": "%lld sesi %@",
    "tr": "%lld oturumlar %@",
    "nl": "%lld sessies %@",
    "pl": "%lld sesje %@",
    "uk": "%lld сеансів %@",
    "ms": "%lld sesi %@"
  },
  "完成次数": {
    "zh-Hant": "完成次数",
    "es": "Sesiones completadas",
    "fr": "Séances terminées",
    "de": "Sitzungen abgeschlossen",
    "pt-BR": "Sessões concluídas",
    "ru": "Сеансы завершены",
    "ar": "اكتملت الجلسات",
    "hi": "सत्र पूर्ण",
    "it": "Sessioni completate",
    "th": "เซสชันเสร็จสมบูรณ์",
    "vi": "Phiên đã hoàn thành",
    "id": "Sesi Selesai",
    "tr": "Tamamlanan Oturumlar",
    "nl": "Sessies voltooid",
    "pl": "Sesje zakończone",
    "uk": "Сеанси завершено",
    "ms": "Sesi Selesai"
  },
  "对不起自己一次": {
    "zh-Hant": "对不起自己一次",
    "es": "lo hiciste bien por ti mismo",
    "fr": "tu as bien fait toi-même",
    "de": "hast es selbst richtig gemacht",
    "pt-BR": "fez certo sozinho",
    "ru": "сделал правильно сам",
    "ar": "فعلت الحق بنفسك",
    "hi": "अपने आप से सही किया",
    "it": "hai fatto bene da solo",
    "th": "ทำถูกต้องด้วยตัวเอง",
    "vi": "tự mình làm đúng",
    "id": "melakukannya dengan benar sendiri",
    "tr": "kendi başına doğruyu yaptın",
    "nl": "heb het zelf goed gedaan",
    "pl": "zrobiłeś to sam",
    "uk": "зробив правильно сам",
    "ms": "melakukan dengan betul sendiri"
  },
  "对得起自己一次": {
    "zh-Hant": "对得起自己一次",
    "es": "lo hiciste bien por ti mismo",
    "fr": "tu as bien fait toi-même",
    "de": "hast es selbst richtig gemacht",
    "pt-BR": "fez certo sozinho",
    "ru": "сделал правильно сам",
    "ar": "فعلت الحق بنفسك",
    "hi": "अपने आप से सही किया",
    "it": "hai fatto bene da solo",
    "th": "ทำถูกต้องด้วยตัวเอง",
    "vi": "tự mình làm đúng",
    "id": "melakukannya dengan benar sendiri",
    "tr": "kendi başına doğruyu yaptın",
    "nl": "heb het zelf goed gedaan",
    "pl": "zrobiłeś to sam",
    "uk": "зробив правильно сам",
    "ms": "melakukan dengan betul sendiri"
  },
  "少": {
    "zh-Hant": "少",
    "es": "Menos",
    "fr": "Moins",
    "de": "Weniger",
    "pt-BR": "Menos",
    "ru": "Меньше",
    "ar": "أقل",
    "hi": "कम",
    "it": "Meno",
    "th": "น้อย",
    "vi": "Ít hơn",
    "id": "Lebih sedikit",
    "tr": "Az",
    "nl": "Minder",
    "pl": "Mniej",
    "uk": "менше",
    "ms": "Kurang"
  },
  "等你回来": {
    "zh-Hant": "等你回来",
    "es": "Esperando por ti",
    "fr": "Dans votre attente",
    "de": "Warten auf Sie",
    "pt-BR": "Esperando por você",
    "ru": "Ждем Вас",
    "ar": "في انتظاركم",
    "hi": "आपका इंतजार",
    "it": "Ti aspetto",
    "th": "รอคุณอยู่",
    "vi": "Đang chờ bạn",
    "id": "Menunggumu",
    "tr": "Seni bekliyor",
    "nl": "Ik wacht op jou",
    "pl": "Czekam na ciebie",
    "uk": "Чекаю на вас",
    "ms": "Menunggu awak"
  },
  "等你开始": {
    "zh-Hant": "等你開始",
    "es": "Listo cuando lo estés",
    "fr": "Prêt quand tu l'es",
    "de": "Bereit, wenn Sie es sind",
    "pt-BR": "Pronto quando você estiver",
    "ru": "Готов, когда вы будете",
    "ar": "جاهز عندما تكون",
    "hi": "तैयार जब आप हैं",
    "it": "Pronto quando lo sei tu",
    "th": "พร้อมเมื่อคุณพร้อม",
    "vi": "Sẵn sàng khi bạn sẵn sàng",
    "id": "Siap ketika Anda siap",
    "tr": "Hazır olduğunuzda hazır",
    "nl": "Klaar wanneer jij dat bent",
    "pl": "Gotowy, kiedy będziesz",
    "uk": "Готовий, коли будеш",
    "ms": "Bersedia apabila anda sudah"
  },
  "心流体验一次": {
    "zh-Hant": "心流体验一次",
    "es": "entró en estado de flujo",
    "fr": "état de flux entré",
    "de": "in den Fließzustand eingetreten",
    "pt-BR": "entrou no estado de fluxo",
    "ru": "вошло в состояние потока",
    "ar": "دخلت حالة التدفق",
    "hi": "प्रवाह स्थिति में प्रवेश किया",
    "it": "entrato nello stato di flusso",
    "th": "เข้าสู่สถานะการไหล",
    "vi": "đã vào trạng thái dòng chảy",
    "id": "memasuki kondisi aliran",
    "tr": "girilen akış durumu",
    "nl": "stroomtoestand binnengegaan",
    "pl": "wszedł w stan przepływu",
    "uk": "введений стан потоку",
    "ms": "memasuki keadaan aliran"
  },
  "总时长": {
    "zh-Hant": "總時長",
    "es": "Duración total",
    "fr": "Durée totale",
    "de": "Gesamtdauer",
    "pt-BR": "Duração total",
    "ru": "Общая продолжительность",
    "ar": "المدة الإجمالية",
    "hi": "कुल अवधि",
    "it": "Durata totale",
    "th": "ระยะเวลารวม",
    "vi": "Tổng thời lượng",
    "id": "Durasi Total",
    "tr": "Toplam Süre",
    "nl": "Totale duur",
    "pl": "Całkowity czas trwania",
    "uk": "Загальна тривалість",
    "ms": "Jumlah Tempoh"
  },
  "本次时长": {
    "zh-Hant": "本次時長",
    "es": "Esta sesión",
    "fr": "Cette séance",
    "de": "Diese Sitzung",
    "pt-BR": "Esta sessão",
    "ru": "Эта сессия",
    "ar": "هذه الجلسة",
    "hi": "इस सत्र",
    "it": "Questa sessione",
    "th": "เซสชั่นนี้",
    "vi": "Phiên này",
    "id": "Sesi ini",
    "tr": "Bu Oturum",
    "nl": "Deze sessie",
    "pl": "Ta sesja",
    "uk": "Ця сесія",
    "ms": "Sesi ini"
  },
  "默认时长": {
    "zh-Hant": "預設時長",
    "es": "Duración predeterminada",
    "fr": "Durée par défaut",
    "de": "Standarddauer",
    "pt-BR": "Duração padrão",
    "ru": "Продолжительность по умолчанию",
    "ar": "المدة الافتراضية",
    "hi": "डिफ़ॉल्ट अवधि",
    "it": "Durata predefinita",
    "th": "ระยะเวลาเริ่มต้น",
    "vi": "Thời lượng mặc định",
    "id": "Durasi Bawaan",
    "tr": "Varsayılan Süre",
    "nl": "Standaardduur",
    "pl": "Domyślny czas trwania",
    "uk": "Тривалість за замовчуванням",
    "ms": "Tempoh Lalai"
  },
  "默认时长会在每次专注结束后自动应用。打开应用后可直接点击「开始专注」，或先调整本次时长。": {
    "zh-Hant": "預設時長会在每次專注結束後自动应用。打開应用後可直接點擊「開始專注」，或先调整本次時長。",
    "es": "La duración predeterminada se aplica después de cada sesión. Toque Iniciar enfoque o ajuste esta sesión primero.",
    "fr": "La durée par défaut s'applique après chaque session. Appuyez sur Démarrer Focus ou ajustez d'abord cette session.",
    "de": "Nach jeder Sitzung gilt die Standarddauer. Tippen Sie auf Fokus starten oder passen Sie diese Sitzung zuerst an.",
    "pt-BR": "A duração padrão se aplica após cada sessão. Toque em Iniciar foco ou ajuste esta sessão primeiro.",
    "ru": "Продолжительность по умолчанию применяется после каждого сеанса. Нажмите «Начать фокус» или сначала настройте этот сеанс.",
    "ar": "تنطبق المدة الافتراضية بعد كل جلسة. اضغط على \"بدء التركيز\" أو اضبط هذه الجلسة أولاً.",
    "hi": "प्रत्येक सत्र के बाद डिफ़ॉल्ट अवधि लागू होती है। स्टार्ट फोकस पर टैप करें या पहले इस सत्र को समायोजित करें।",
    "it": "La durata predefinita si applica dopo ogni sessione. Tocca Avvia focus o modifica prima questa sessione.",
    "th": "ระยะเวลาเริ่มต้นจะใช้หลังจากแต่ละเซสชัน แตะเริ่มโฟกัสหรือปรับเซสชันนี้ก่อน",
    "vi": "Thời lượng mặc định áp dụng sau mỗi phiên. Nhấn vào Bắt đầu lấy nét hoặc điều chỉnh phiên này trước.",
    "id": "Durasi default berlaku setelah setiap sesi. Ketuk Mulai Fokus atau sesuaikan sesi ini terlebih dahulu.",
    "tr": "Varsayılan süre her oturumdan sonra geçerlidir. Odaklanmayı Başlat'a dokunun veya önce bu oturumu ayarlayın.",
    "nl": "De standaardduur geldt na elke sessie. Tik op Start Focus of pas eerst deze sessie aan.",
    "pl": "Domyślny czas trwania obowiązuje po każdej sesji. Kliknij opcję Rozpocznij fokus lub najpierw dostosuj tę sesję.",
    "uk": "Тривалість за замовчуванням застосовується після кожного сеансу. Натисніть «Почати фокус» або спочатку налаштуйте цей сеанс.",
    "ms": "Tempoh lalai digunakan selepas setiap sesi. Ketik Mulakan Fokus atau laraskan sesi ini dahulu."
  },
  "未完成": {
    "zh-Hant": "未完成",
    "es": "No completado",
    "fr": "Non terminé",
    "de": "Nicht abgeschlossen",
    "pt-BR": "Não concluído",
    "ru": "Не завершено",
    "ar": "لم يكتمل",
    "hi": "पूरा नहीं हुआ",
    "it": "Non completato",
    "th": "ไม่เสร็จ",
    "vi": "Chưa hoàn thành",
    "id": "Tidak selesai",
    "tr": "Tamamlanmadı",
    "nl": "Niet voltooid",
    "pl": "Nieukończone",
    "uk": "Не завершено",
    "ms": "Tidak selesai"
  },
  "还没有完成的专注": {
    "zh-Hant": "還没有完成的專注",
    "es": "Aún no hay sesiones completadas",
    "fr": "Aucune session terminée pour l'instant",
    "de": "Noch keine abgeschlossenen Sitzungen",
    "pt-BR": "Nenhuma sessão concluída ainda",
    "ru": "Завершенных сессий еще нет",
    "ar": "لا توجد جلسات مكتملة حتى الآن",
    "hi": "अभी तक कोई सत्र पूरा नहीं हुआ",
    "it": "Nessuna sessione ancora completata",
    "th": "ยังไม่มีเซสชั่นที่เสร็จสมบูรณ์",
    "vi": "Chưa có phiên nào hoàn thành",
    "id": "Belum ada sesi yang selesai",
    "tr": "Henüz tamamlanan oturum yok",
    "nl": "Nog geen voltooide sessies",
    "pl": "Nie ma jeszcze ukończonych sesji",
    "uk": "Ще немає завершених сеансів",
    "ms": "Tiada sesi selesai lagi"
  },
  "每完成一次种一棵树": {
    "zh-Hant": "每完成一次种一棵树",
    "es": "Un árbol plantado por sesión.",
    "fr": "Un arbre planté par séance",
    "de": "Pro Sitzung wird ein Baum gepflanzt",
    "pt-BR": "Uma árvore plantada por sessão",
    "ru": "За один сеанс посажено одно дерево",
    "ar": "تزرع شجرة واحدة في كل جلسة",
    "hi": "प्रति सत्र एक पेड़ लगाया गया",
    "it": "Un albero piantato per sessione",
    "th": "ปลูกต้นไม้หนึ่งต้นต่อเซสชัน",
    "vi": "Mỗi buổi trồng một cây",
    "id": "Satu pohon ditanam per sesi",
    "tr": "Her oturuma bir ağaç dikildi",
    "nl": "Per sessie wordt één boom geplant",
    "pl": "Jedno drzewo sadzone na sesję",
    "uk": "За один сеанс висаджують одне дерево",
    "ms": "Satu pokok ditanam setiap sesi"
  },
  "深度思考一次": {
    "zh-Hant": "深度思考一次",
    "es": "sesión de pensamiento profundo",
    "fr": "séance de réflexion profonde",
    "de": "tiefe Denksitzung",
    "pt-BR": "sessão de reflexão profunda",
    "ru": "сеанс глубокого размышления",
    "ar": "جلسة تفكير عميق",
    "hi": "गहन चिंतन सत्र",
    "it": "sessione di riflessione profonda",
    "th": "เซสชันการคิดอย่างลึกซึ้ง",
    "vi": "buổi suy nghĩ sâu sắc",
    "id": "sesi berpikir mendalam",
    "tr": "derin düşünme oturumu",
    "nl": "diepe denksessie",
    "pl": "sesja głębokiego myślenia",
    "uk": "сеанс глибокого мислення",
    "ms": "sesi berfikir secara mendalam"
  },
  "离目标更近一步": {
    "zh-Hant": "离目标更近一步",
    "es": "un paso más cerca de tu objetivo",
    "fr": "un pas de plus vers votre objectif",
    "de": "Ihrem Ziel einen Schritt näher",
    "pt-BR": "um passo mais perto do seu objetivo",
    "ru": "на один шаг ближе к вашей цели",
    "ar": "خطوة واحدة أقرب إلى هدفك",
    "hi": "अपने लक्ष्य के एक कदम और करीब",
    "it": "un passo avanti verso il tuo obiettivo",
    "th": "ใกล้เป้าหมายของคุณไปอีกก้าวหนึ่ง",
    "vi": "một bước gần hơn tới mục tiêu của bạn",
    "id": "satu langkah lebih dekat ke tujuan Anda",
    "tr": "hedefinize bir adım daha yaklaştınız",
    "nl": "een stap dichter bij jouw doel",
    "pl": "o krok bliżej celu",
    "uk": "на крок ближче до вашої мети",
    "ms": "selangkah lebih dekat dengan matlamat anda"
  },
  "暂停": {
    "zh-Hant": "暂停",
    "es": "Pausa",
    "fr": "Pause",
    "de": "Pause",
    "pt-BR": "Pausa",
    "ru": "Пауза",
    "ar": "يوقف",
    "hi": "विराम",
    "it": "Pausa",
    "th": "หยุดชั่วคราว",
    "vi": "Tạm dừng",
    "id": "Berhenti sebentar",
    "tr": "Duraklat",
    "nl": "Pauze",
    "pl": "Pauza",
    "uk": "Пауза",
    "ms": "jeda"
  },
  "倒计时": {
    "zh-Hant": "倒计時",
    "es": "Minutero",
    "fr": "Minuteur",
    "de": "Timer",
    "pt-BR": "Temporizador",
    "ru": "Таймер",
    "ar": "الموقت",
    "hi": "घड़ी",
    "it": "Timer",
    "th": "ตัวจับเวลา",
    "vi": "hẹn giờ",
    "id": "pengatur waktu",
    "tr": "Zamanlayıcı",
    "nl": "Timer",
    "pl": "Regulator czasowy",
    "uk": "Таймер",
    "ms": "Pemasa"
  },
  "每日记录": {
    "zh-Hant": "每日記录",
    "es": "Historia diaria",
    "fr": "Histoire quotidienne",
    "de": "Tägliche Geschichte",
    "pt-BR": "História Diária",
    "ru": "Ежедневная история",
    "ar": "التاريخ اليومي",
    "hi": "दैनिक इतिहास",
    "it": "Storia quotidiana",
    "th": "ประวัติประจำวัน",
    "vi": "Lịch sử hàng ngày",
    "id": "Sejarah Harian",
    "tr": "Günlük Geçmiş",
    "nl": "Dagelijkse geschiedenis",
    "pl": "Historia codzienna",
    "uk": "Щоденна історія",
    "ms": "Sejarah Harian"
  },
  "暂无记录，开始第一次专注吧": {
    "zh-Hant": "暂无記录，開始第一次專注吧",
    "es": "Aún no hay registros: comience su primera sesión",
    "fr": "Aucun enregistrement pour l'instant : démarrez votre première session",
    "de": "Noch keine Aufzeichnungen – starten Sie Ihre erste Sitzung",
    "pt-BR": "Ainda não há registros — inicie sua primeira sessão",
    "ru": "Записей пока нет — начните первую сессию",
    "ar": "لا توجد سجلات حتى الآن — ابدأ جلستك الأولى",
    "hi": "अभी तक कोई रिकॉर्ड नहीं - अपना पहला सत्र शुरू करें",
    "it": "Ancora nessun record: inizia la tua prima sessione",
    "th": "ยังไม่มีบันทึก — เริ่มเซสชั่นแรกของคุณ",
    "vi": "Chưa có bản ghi nào - hãy bắt đầu phiên đầu tiên của bạn",
    "id": "Belum ada catatan — mulai sesi pertama Anda",
    "tr": "Henüz kayıt yok — ilk oturumunuzu başlatın",
    "nl": "Nog geen gegevens: start uw eerste sessie",
    "pl": "Nie ma jeszcze żadnych rekordów — rozpocznij pierwszą sesję",
    "uk": "Записів ще немає — почніть свій перший сеанс",
    "ms": "Tiada rekod lagi — mulakan sesi pertama anda"
  },
  "状态不错": {
    "zh-Hant": "状態不错",
    "es": "haciendo bien",
    "fr": "Ça va bien",
    "de": "Machst gut",
    "pt-BR": "Indo bem",
    "ru": "Дела идут хорошо",
    "ar": "القيام بعمل جيد",
    "hi": "अच्छी तरह से कर रही है",
    "it": "Sto bene",
    "th": "ทำได้ดี",
    "vi": "làm tốt",
    "id": "Baik-baik saja",
    "tr": "İyi gidiyor",
    "nl": "Het gaat goed",
    "pl": "Dobrze sobie radzi",
    "uk": "Добре",
    "ms": "Berbuat baik"
  },
  "陪伴中": {
    "zh-Hant": "陪伴中",
    "es": "Haciéndote compañía",
    "fr": "Te tenir compagnie",
    "de": "Wir leisten Ihnen Gesellschaft",
    "pt-BR": "Te fazendo companhia",
    "ru": "Составляю тебе компанию",
    "ar": "الحفاظ على شركتك",
    "hi": "आपका साथ बनाए रखना",
    "it": "Tenerti compagnia",
    "th": "คอยเป็นเพื่อนคุณ",
    "vi": "Luôn đồng hành cùng bạn",
    "id": "Menemani Anda",
    "tr": "Sana arkadaşlık etmek",
    "nl": "Jou gezelschap houden",
    "pl": "Dotrzymam Ci towarzystwa",
    "uk": "Складаю тобі компанію",
    "ms": "Menemani anda"
  },
  "陪你专注中…": {
    "zh-Hant": "陪你專注中…",
    "es": "Enfocándonos contigo...",
    "fr": "Se concentrer avec vous…",
    "de": "Konzentrieren Sie sich mit Ihnen…",
    "pt-BR": "Focando em você…",
    "ru": "Сосредоточившись на тебе…",
    "ar": "التركيز معك...",
    "hi": "आपके साथ ध्यान केंद्रित कर रहा हूँ...",
    "it": "Concentrarsi su di te...",
    "th": "มุ่งเน้นไปที่คุณ...",
    "vi": "Tập trung cùng bạn…",
    "id": "Fokus denganmu…",
    "tr": "Seninle odaklanmak…",
    "nl": "Samen met jou focussen...",
    "pl": "Skupiając się na Tobie…",
    "uk": "Зосереджуючись на тобі…",
    "ms": "Fokus dengan anda…"
  },
  "点「开始专注」陪我吧": {
    "zh-Hant": "點「開始專注」陪我吧",
    "es": "Toca Iniciar enfoque para unirte a mí",
    "fr": "Appuyez sur Démarrer Focus pour me rejoindre",
    "de": "Tippen Sie auf Fokus starten, um sich mir anzuschließen",
    "pt-BR": "Toque em Iniciar foco para se juntar a mim",
    "ru": "Нажмите «Начать фокус», чтобы присоединиться ко мне.",
    "ar": "اضغط على \"بدء التركيز\" للانضمام إلي",
    "hi": "मुझसे जुड़ने के लिए स्टार्ट फोकस पर टैप करें",
    "it": "Tocca Avvia focus per unirti a me",
    "th": "แตะเริ่มโฟกัสเพื่อเข้าร่วมกับฉัน",
    "vi": "Nhấn vào Bắt đầu tập trung để tham gia cùng tôi",
    "id": "Ketuk Mulai Fokus untuk bergabung dengan saya",
    "tr": "Bana katılmak için Odaklanmayı Başlat'a dokunun",
    "nl": "Tik op Start Focus om met mij mee te doen",
    "pl": "Stuknij opcję Uruchom Fokus, aby do mnie dołączyć",
    "uk": "Натисніть «Почати фокус», щоб приєднатися до мене",
    "ms": "Ketik Mula Fokus untuk menyertai saya"
  },
  "版本": {
    "zh-Hant": "版本",
    "es": "Versión",
    "fr": "Version",
    "de": "Version",
    "pt-BR": "Versão",
    "ru": "Версия",
    "ar": "إصدار",
    "hi": "संस्करण",
    "it": "Versione",
    "th": "เวอร์ชัน",
    "vi": "Phiên bản",
    "id": "Versi",
    "tr": "Sürüm",
    "nl": "Versie",
    "pl": "Wersja",
    "uk": "Версія",
    "ms": "Versi"
  },
  "猫粮 +1": {
    "zh-Hant": "貓粮 +1",
    "es": "Tratar +1",
    "fr": "Traiter +1",
    "de": "Behandle +1",
    "pt-BR": "Tratar +1",
    "ru": "Угощение +1",
    "ar": "علاج +1",
    "hi": "+1 का इलाज करें",
    "it": "Tratta +1",
    "th": "ปฏิบัติต่อ +1",
    "vi": "Xử lý +1",
    "id": "Perlakukan +1",
    "tr": "+1'i tedavi et",
    "nl": "Behandel +1",
    "pl": "Leczenie +1",
    "uk": "Пригощати +1",
    "ms": "Rawat +1"
  },
  "知道了": {
    "zh-Hant": "知道了",
    "es": "Entiendo",
    "fr": "J'ai compris",
    "de": "Habe es",
    "pt-BR": "Entendi",
    "ru": "Понятно",
    "ar": "فهمتها",
    "hi": "समझ गया",
    "it": "Fatto",
    "th": "เข้าใจแล้ว",
    "vi": "Hiểu rồi",
    "id": "Mengerti",
    "tr": "Anladım",
    "nl": "Ik heb het",
    "pl": "Rozumiem",
    "uk": "зрозумів",
    "ms": "faham"
  },
  "统计": {
    "zh-Hant": "統计",
    "es": "Estadísticas",
    "fr": "Statistiques",
    "de": "Statistiken",
    "pt-BR": "Estatísticas",
    "ru": "Статистика",
    "ar": "احصائيات",
    "hi": "आँकड़े",
    "it": "Statistiche",
    "th": "สถิติ",
    "vi": "Thống kê",
    "id": "Statistik",
    "tr": "İstatistikler",
    "nl": "Statistieken",
    "pl": "Statystyki",
    "uk": "статистика",
    "ms": "Statistik"
  },
  "继续": {
    "zh-Hant": "继續",
    "es": "Reanudar",
    "fr": "CV",
    "de": "Wieder aufnehmen",
    "pt-BR": "Retomar",
    "ru": "Резюме",
    "ar": "سيرة ذاتية",
    "hi": "फिर शुरू करना",
    "it": "Riprendere",
    "th": "ประวัติย่อ",
    "vi": "Bản tóm tắt",
    "id": "Melanjutkan",
    "tr": "Sürdürmek",
    "nl": "Cv",
    "pl": "Wznawiać",
    "uk": "Резюме",
    "ms": "Sambung semula"
  },
  "累计完成": {
    "zh-Hant": "累计完成",
    "es": "Total completado",
    "fr": "Total réalisé",
    "de": "Insgesamt abgeschlossen",
    "pt-BR": "Total concluído",
    "ru": "Всего выполнено",
    "ar": "إجمالي مكتمل",
    "hi": "कुल पूर्ण",
    "it": "Totale completato",
    "th": "รวมแล้วเสร็จ",
    "vi": "Tổng số đã hoàn thành",
    "id": "Jumlah Selesai",
    "tr": "Toplam Tamamlanan",
    "nl": "Totaal voltooid",
    "pl": "Razem ukończono",
    "uk": "Всього виконано",
    "ms": "Jumlah Selesai"
  },
  "累计时长": {
    "zh-Hant": "累计時長",
    "es": "Duración total",
    "fr": "Durée totale",
    "de": "Gesamtdauer",
    "pt-BR": "Duração total",
    "ru": "Общая продолжительность",
    "ar": "المدة الإجمالية",
    "hi": "कुल अवधि",
    "it": "Durata totale",
    "th": "ระยะเวลารวม",
    "vi": "Tổng thời lượng",
    "id": "Durasi Total",
    "tr": "Toplam Süre",
    "nl": "Totale duur",
    "pl": "Całkowity czas trwania",
    "uk": "Загальна тривалість",
    "ms": "Jumlah Tempoh"
  },
  "结束": {
    "zh-Hant": "結束",
    "es": "Fin",
    "fr": "Fin",
    "de": "Ende",
    "pt-BR": "Fim",
    "ru": "Конец",
    "ar": "نهاية",
    "hi": "अंत",
    "it": "FINE",
    "th": "จบ",
    "vi": "Kết thúc",
    "id": "Akhir",
    "tr": "Son",
    "nl": "Einde",
    "pl": "Koniec",
    "uk": "Кінець",
    "ms": "tamat"
  },
  "设置": {
    "zh-Hant": "设置",
    "es": "Ajustes",
    "fr": "Paramètres",
    "de": "Einstellungen",
    "pt-BR": "Configurações",
    "ru": "Настройки",
    "ar": "إعدادات",
    "hi": "सेटिंग्स",
    "it": "Impostazioni",
    "th": "การตั้งค่า",
    "vi": "Cài đặt",
    "id": "Pengaturan",
    "tr": "Ayarlar",
    "nl": "Instellingen",
    "pl": "Ustawienia",
    "uk": "Налаштування",
    "ms": "tetapan"
  },
  "过去 26 周每日专注情况，颜色越深表示越活跃": {
    "zh-Hant": "過去 26 周每日專注情况，颜色越深表示越活跃",
    "es": "Enfoque diario durante las últimas 26 semanas. Más oscuro = más activo.",
    "fr": "Focus quotidien au cours des 26 dernières semaines. Plus sombre = plus actif.",
    "de": "Täglicher Fokus in den letzten 26 Wochen. Dunkler = aktiver.",
    "pt-BR": "Foco diário nas últimas 26 semanas. Mais escuro = mais ativo.",
    "ru": "Ежедневное внимание за последние 26 недель. Темнее = более активный.",
    "ar": "التركيز اليومي على مدار الـ 26 أسبوعًا الماضية. أغمق = أكثر نشاطا.",
    "hi": "पिछले 26 सप्ताहों में दैनिक फोकस। गहरा = अधिक सक्रिय।",
    "it": "Focus quotidiano nelle ultime 26 settimane. Più scuro = più attivo.",
    "th": "โฟกัสรายวันในช่วง 26 สัปดาห์ที่ผ่านมา เข้มขึ้น = กระตือรือร้นมากขึ้น",
    "vi": "Tập trung hàng ngày trong 26 tuần qua. Tối hơn = năng động hơn.",
    "id": "Fokus harian selama 26 minggu terakhir. Darker = more active.",
    "tr": "Son 26 hafta boyunca günlük odaklanma. Daha koyu = daha aktif.",
    "nl": "Dagelijkse focus gedurende de afgelopen 26 weken. Donkerder = actiever.",
    "pl": "Codzienne skupienie na przestrzeni ostatnich 26 tygodni. Ciemniejszy = bardziej aktywny.",
    "uk": "Щоденний фокус протягом останніх 26 тижнів. Темніше = активніше.",
    "ms": "Fokus harian sepanjang 26 minggu yang lalu. Lebih gelap = lebih aktif."
  },
  "安静地趴在你旁边…": {
    "zh-Hant": "安静地趴在你旁边…",
    "es": "Descansando tranquilamente a tu lado...",
    "fr": "Se reposer tranquillement à côté de vous…",
    "de": "Ruhig neben dir ruhen…",
    "pt-BR": "Descansando silenciosamente ao seu lado…",
    "ru": "Тихо отдыхаю рядом с тобой…",
    "ar": "يستريح بهدوء بجانبك...",
    "hi": "चुपचाप तुम्हारे पास आराम कर रहा हूँ...",
    "it": "Riposando tranquillamente accanto a te...",
    "th": "อยู่เคียงข้างคุณอย่างเงียบๆ…",
    "vi": "Lặng lẽ nghỉ ngơi bên cạnh bạn…",
    "id": "Beristirahat dengan tenang di sampingmu…",
    "tr": "Sessizce yanında dinlenmek…",
    "nl": "Rustig naast je liggen...",
    "pl": "Cicho odpoczywam obok Ciebie…",
    "uk": "Тихо спочиває поруч з тобою…",
    "ms": "Diam-diam berehat di sebelah anda…"
  },
  "准备开始": {
    "zh-Hant": "準備開始",
    "es": "Listo",
    "fr": "Prêt",
    "de": "Bereit",
    "pt-BR": "Preparar",
    "ru": "Готовый",
    "ar": "مستعد",
    "hi": "तैयार",
    "it": "Pronto",
    "th": "พร้อม",
    "vi": "Sẵn sàng",
    "id": "Siap",
    "tr": "Hazır",
    "nl": "Klaar",
    "pl": "Gotowy",
    "uk": "Готовий",
    "ms": "sedia"
  },
  "热力图加载失败，请重启应用": {
    "zh-Hant": "熱力圖加載失败，請重啟应用",
    "es": "No se pudo cargar el mapa de calor. Reinicie la aplicación.",
    "fr": "Échec du chargement de la carte thermique. Veuillez redémarrer l'application.",
    "de": "Heatmap konnte nicht geladen werden. Bitte starten Sie die App neu.",
    "pt-BR": "Falha ao carregar o mapa de calor. Por favor reinicie o aplicativo.",
    "ru": "Не удалось загрузить тепловую карту. Пожалуйста, перезапустите приложение.",
    "ar": "فشل تحميل خريطة الحرارة. يرجى إعادة تشغيل التطبيق.",
    "hi": "हीटमैप लोड करने में विफल. कृपया ऐप पुनः प्रारंभ करें.",
    "it": "Impossibile caricare la mappa termica. Riavvia l'app.",
    "th": "ไม่สามารถโหลดแผนที่ความร้อน โปรดรีสตาร์ทแอป",
    "vi": "Không tải được bản đồ nhiệt. Vui lòng khởi động lại ứng dụng.",
    "id": "Gagal memuat peta panas. Silakan mulai ulang aplikasinya.",
    "tr": "Isı haritası yüklenemedi. Lütfen uygulamayı yeniden başlatın.",
    "nl": "Kan heatmap niet laden. Start de app opnieuw.",
    "pl": "Nie udało się załadować mapy cieplnej. Uruchom ponownie aplikację.",
    "uk": "Не вдалося завантажити теплову карту. Перезапустіть програму.",
    "ms": "Gagal memuatkan peta haba. Sila mulakan semula apl."
  },
  "桌面浮窗": {
    "zh-Hant": "桌面浮窗",
    "es": "Flotador de escritorio",
    "fr": "Flotteur de bureau",
    "de": "Desktop-Float",
    "pt-BR": "Flutuação na área de trabalho",
    "ru": "Настольный поплавок",
    "ar": "تعويم سطح المكتب",
    "hi": "डेस्कटॉप फ़्लोट",
    "it": "Desktop mobile",
    "th": "เดสก์ท็อปโฟลต",
    "vi": "Phao để bàn",
    "id": "Desktop Mengambang",
    "tr": "Masaüstü Kayan",
    "nl": "Bureaublad zweeft",
    "pl": "Pulpit pływający",
    "uk": "Плаваючий робочий стіл",
    "ms": "Desktop Terapung"
  },
  "高效成长一次": {
    "zh-Hant": "高效成長一次",
    "es": "crecimiento productivo",
    "fr": "croissance productive",
    "de": "produktives Wachstum",
    "pt-BR": "crescimento produtivo",
    "ru": "продуктивный рост",
    "ar": "النمو الإنتاجي",
    "hi": "उत्पादक विकास",
    "it": "crescita produttiva",
    "th": "การเจริญเติบโตที่มีประสิทธิผล",
    "vi": "tăng trưởng năng suất",
    "id": "pertumbuhan produktif",
    "tr": "üretken büyüme",
    "nl": "productieve groei",
    "pl": "produktywny wzrost",
    "uk": "продуктивне зростання",
    "ms": "pertumbuhan yang produktif"
  }
}